airtake/__init__.py
airtake/client.py
airtake/props.py
airtake/py.typed
airtake/types.py
airtake/utils.py
airtake-0.3.1.dist-info/METADATA
airtake-0.3.1.dist-info/WHEEL
airtake-0.3.1.dist-info/RECORD
