Metadata-Version: 2.4
Name: airtake
Version: 0.3.1
Summary: Airtake
Author-email: Bae Junehyeon <devunt@gmail.com>
Requires-Python: >=3.10
